pynanalogue/__init__.py
pynanalogue/pynanalogue.abi3.so
pynanalogue-0.1.6.dist-info/METADATA
pynanalogue-0.1.6.dist-info/WHEEL
pynanalogue-0.1.6.dist-info/licenses/LICENSE.txt
pynanalogue-0.1.6.dist-info/RECORD
