Metadata-Version: 2.4
Name: pynanalogue
Version: 0.1.6
Classifier: Development Status :: 3 - Alpha
Classifier: Intended Audience :: Science/Research
Classifier: Topic :: Scientific/Engineering :: Bio-Informatics
Classifier: License :: OSI Approved :: MIT License
Classifier: Programming Language :: Rust
Classifier: Programming Language :: Python :: 3
Classifier: Programming Language :: Python :: 3.9
Classifier: Programming Language :: Python :: 3.10
Classifier: Programming Language :: Python :: 3.11
Classifier: Programming Language :: Python :: 3.12
Classifier: Programming Language :: Python :: 3.13
Classifier: Programming Language :: Python :: 3.14
Requires-Dist: polars>=1.36.1
Requires-Dist: pytest>=7.0 ; extra == 'dev'
Requires-Dist: pytest-cov>=4.0 ; extra == 'dev'
Requires-Dist: pytest-benchmark>=4.0 ; extra == 'dev'
Requires-Dist: ruff>=0.1.0 ; extra == 'dev'
Provides-Extra: dev
License-File: LICENSE.txt
Summary: Python bindings for Nanalogue: single-molecule BAM/Mod-BAM analysis
Keywords: bioinformatics,genomics,bam,modifications,single-molecule,nanopore
Author-email: Sathish Thiyagarajan <mail@unintegrable.com>
Maintainer-email: Sathish Thiyagarajan <mail@unintegrable.com>
License-Expression: MIT
Requires-Python: >=3.9
Project-URL: Changelog, https://github.com/DNAReplicationLab/pynanalogue/blob/main/CHANGELOG.md
Project-URL: Documentation, https://www.nanalogue.com
Project-URL: Homepage, https://www.nanalogue.com
Project-URL: Issues, https://github.com/DNAReplicationLab/pynanalogue/issues
Project-URL: Repository, https://github.com/DNAReplicationLab/pynanalogue
